Workbook

Sheet Sheet1
A1: Model | B1: ISIN | C1: Name | D1: Asset Class | E1: Sub Asset Class | F1: Weighting
A2: Managed Active Portfolio 9 | B2: GB00BG371S47 | C2: QI North American Equity | D2: =VLOOKUP(B2,Sheet2!A:D,3,FALSE) -> Equity | E2: =VLOOKUP(B2,Sheet2!A:D,4,FALSE) -> US | F2: 0.0966
A3: Managed Active Portfolio 9 | B3: GB00BZ191K76 | C3: QI US Equity Income | D3: =VLOOKUP(B3,Sheet2!A:D,3,FALSE) -> Equity | E3: =VLOOKUP(B3,Sheet2!A:D,4,FALSE) -> US | F3: 0.0966
A4: Managed Active Portfolio 9 | B4: GB00B88BTC50 | C4: QI Japanese Equity | D4: =VLOOKUP(B4,Sheet2!A:D,3,FALSE) -> Equity | E4: =VLOOKUP(B4,Sheet2!A:D,4,FALSE) -> Japan | F4: 0.062
A5: Managed Active Portfolio 9 | B5: GB00B8L0QW80 | C5: QI Europe (ex UK) Equity | D5: =VLOOKUP(B5,Sheet2!A:D,3,FALSE) -> Equity | E5: =VLOOKUP(B5,Sheet2!A:D,4,FALSE) -> Europe ex UK | F5: 0.0608
A6: Managed Active Portfolio 9 | B6: GB00B8SFP856 | C6: QI Global Equity Value | D6: =VLOOKUP(B6,Sheet2!A:D,3,FALSE) -> Equity | E6: =VLOOKUP(B6,Sheet2!A:D,4,FALSE) -> Global | F6: 0.0586
A7: Managed Active Portfolio 9 | B7: GB00B98WPN88 | C7: QI Europe (ex UK) Equity Growth | D7: =VLOOKUP(B7,Sheet2!A:D,3,FALSE) -> Equity | E7: =VLOOKUP(B7,Sheet2!A:D,4,FALSE) -> Europe ex UK | F7: 0.0456
A8: Managed Active Portfolio 9 | B8: GB00BD4HJ668 | C8: QI Europe (ex UK) Equity Income | D8: =VLOOKUP(B8,Sheet2!A:D,3,FALSE) -> Equity | E8: =VLOOKUP(B8,Sheet2!A:D,4,FALSE) -> Europe ex UK | F8: 0.0456
A9: Managed Active Portfolio 9 | B9: GB00B9947151 | C9: QI UK Equity Large Cap Income | D9: =VLOOKUP(B9,Sheet2!A:D,3,FALSE) -> Equity | E9: =VLOOKUP(B9,Sheet2!A:D,4,FALSE) -> UK | F9: 0.0421
A10: Managed Active Portfolio 9 | B10: GB00B7J9FJ04 | C10: QI UK Equity Opportunities | D10: =VLOOKUP(B10,Sheet2!A:D,3,FALSE) -> Equity | E10: =VLOOKUP(B10,Sheet2!A:D,4,FALSE) -> UK | F10: 0.0373
A11: Managed Active Portfolio 9 | B11: GB00BFWK8976 | C11: QI UK Equity | D11: =VLOOKUP(B11,Sheet2!A:D,3,FALSE) -> Equity | E11: =VLOOKUP(B11,Sheet2!A:D,4,FALSE) -> UK | F11: 0.036
A12: Managed Active Portfolio 9 | B12: GB00B8KPPJ41 | C12: QI Asia Pacific (ex Japan) Equity | D12: =VLOOKUP(B12,Sheet2!A:D,3,FALSE) -> Equity | E12: =VLOOKUP(B12,Sheet2!A:D,4,FALSE) -> Asia ex Japan | F12: 0.0359
A13: Managed Active Portfolio 9 | B13: GB00B98WR877 | C13: QI US Equity Small/Mid Cap | D13: =VLOOKUP(B13,Sheet2!A:D,3,FALSE) -> Equity | E13: =VLOOKUP(B13,Sheet2!A:D,4,FALSE) -> US | F13: 0.0354
... A282: Managed Active Portfolio 10 | B282: GB00B990Y346 | C282: QI China Equity | D282: =VLOOKUP(B282,Sheet2!A:D,3,FALSE) -> Equity | E282: =VLOOKUP(B282,Sheet2!A:D,4,FALSE) -> Emerging Markets | F282: 0.008

Sheet Sheet2
A1: ISIN | B1: Fund Name | C1: Asset Class | D1: Sub Asset Class
A2: IE00B4W0NH34 | B2: Pimco Dynamic Bond | C2: Fixed Income | D2: Global Aggregate
A3: GB00BD2PF085 | B3: QI Absolute Return Bond | C3: Alternative | D3: Alternative
A4: GB00BG371T53 | B4: QI GEAR | C4: Alternative | D4: Alternative
A5: GB00BG371S47 | B5: QI North American Equity | C5: Equity | D5: US
A6: GB00BZ191K76 | B6: QI US Equity Income | C6: Equity | D6: US
A7: GB00B9947151 | B7: QI UK Equity Large Cap Income | C7: Equity | D7: UK
A8: GB00B88BTC50 | B8: QI Japanese Equity | C8: Equity | D8: Japan
A9: GB00B7J9FJ04 | B9: QI UK Equity Opportunities | C9: Equity | D9: UK
A10: GB00BFWK8976 | B10: QI UK Equity | C10: Equity | D10: UK
A11: GB00B8L0QW80 | B11: QI Europe (ex UK) Equity | C11: Equity | D11: Europe ex UK
A12: LU2255680576 | B12: Aviva Global Sovereign Bond | C12: Fixed Income | D12: Global Govt
... A41: GB00BG371R30 | B41: QI Asia Pacific | C41: Equity | D41: Asia ex Japan
